pyvet/__init__.py
pyvet/benefits/__init__.py
pyvet/benefits/claims/__init__.py
pyvet/benefits/claims/api.py
pyvet/benefits/intake/__init__.py
pyvet/benefits/intake/api.py
pyvet/benefits/reference/__init__.py
pyvet/benefits/reference/api.py
pyvet/client.py
pyvet/creds.py
pyvet/facilities/__init__.py
pyvet/facilities/api.py
pyvet/forms/__init__.py
pyvet/forms/api.py
pyvet/health/__init__.py
pyvet/health/community_care/__init__.py
pyvet/health/community_care/api.py
pyvet/health/patient_health/__init__.py
pyvet/health/patient_health/api.py
pyvet/health/provider/__init__.py
pyvet/health/provider/api.py
pyvet/json_alias.py
pyvet/token_scheduler.py
pyvet/veteran/__init__.py
pyvet/veteran/confirmation/__init__.py
pyvet/veteran/confirmation/api.py
pyvet/veteran/verification/__init__.py
pyvet/veteran/verification/api.py
pyvet-0.1.0.dist-info/LICENSE
pyvet-0.1.0.dist-info/METADATA
pyvet-0.1.0.dist-info/WHEEL
pyvet-0.1.0.dist-info/RECORD
