Metadata-Version: 2.1
Name: pyvet
Version: 0.1.0
Summary: Python library to retrieve veteran data from the Department of Veterans Affairs
License: Apache-2.0
Author: cterrazas2
Author-email: 12790854+cterrazas2@users.noreply.github.com
Requires-Python: >=3.10,<4.0
Classifier: License :: OSI Approved :: Apache Software License
Classifier: Programming Language :: Python :: 3
Classifier: Programming Language :: Python :: 3.10
Classifier: Programming Language :: Python :: 3.11
Requires-Dist: oidc-client (>=0.2.3,<0.3.0)
Requires-Dist: pandas (>=1.5.0,<2.0.0)
Requires-Dist: requests (>=2.28.1,<3.0.0)
